Workbook
Name Slicer_Coffee_Name: #N/A
Name Slicer_Months__Date1: #N/A
Name Slicer_Payment_Method1: #N/A

Sheet Raw Data
A1: date | B1: datetime | C1: cash_type | D1: card | E1: money | F1: coffee_name
A2: 45352 | B2: 45352.428 | C2: card | D2: ANON-0000-0000-0001 | E2: 387 | F2: Latte
A3: 45352 | B3: 45352.513 | C3: card | D3: ANON-0000-0000-0002 | E3: 387 | F3: Hot Chocolate
A4: 45352 | B4: 45352.514 | C4: card | D4: ANON-0000-0000-0002 | E4: 387 | F4: Hot Chocolate
A5: 45352 | B5: 45352.574 | C5: card | D5: ANON-0000-0000-0003 | E5: 289 | F5: Americano
A6: 45352 | B6: 45352.575 | C6: card | D6: ANON-0000-0000-0004 | E6: 387 | F6: Latte
A7: 45352 | B7: 45352.653 | C7: card | D7: ANON-0000-0000-0005 | E7: 338 | F7: Americano with Milk
A8: 45352 | B8: 45352.68 | C8: card | D8: ANON-0000-0000-0006 | E8: 387 | F8: Hot Chocolate
A9: 45352 | B9: 45352.777 | C9: card | D9: ANON-0000-0000-0007 | E9: 338 | F9: Americano with Milk
A10: 45352 | B10: 45352.807 | C10: card | D10: ANON-0000-0000-0008 | E10: 387 | F10: Cocoa
A11: 45352 | B11: 45352.808 | C11: card | D11: ANON-0000-0000-0008 | E11: 338 | F11: Americano with Milk
A12: 45352 | B12: 45352.812 | C12: card | D12: ANON-0000-0000-0009 | E12: 338 | F12: Americano with Milk
A13: 45353 | B13: 45353.432 | C13: card | D13: ANON-0000-0000-0010 | E13: 289 | F13: Americano
A14: 45353 | B14: 45353.438 | C14: cash | E14: 400 | F14: Latte
A15: 45353 | B15: 45353.446 | C15: card | D15: ANON-0000-0000-0011 | E15: 338 | F15: Americano with Milk
A16: 45353 | B16: 45353.5 | C16: card | D16: ANON-0000-0000-0012 | E16: 338 | F16: Americano with Milk
A17: 45353 | B17: 45353.61 | C17: card | D17: ANON-0000-0000-0013 | E17: 289 | F17: Americano
A18: 45353 | B18: 45353.693 | C18: card | D18: ANON-0000-0000-0014 | E18: 338 | F18: Americano with Milk
A19: 45353 | B19: 45353.733 | C19: card | D19: ANON-0000-0000-0004 | E19: 289 | F19: Americano
A20: 45354 | B20: 45354.424 | C20: cash | E20: 400 | F20: Latte
A21: 45354 | B21: 45354.436 | C21: card | D21: ANON-0000-0000-0015 | E21: 387 | F21: Latte
A22: 45354 | B22: 45354.482 | C22: card | D22: ANON-0000-0000-0016 | E22: 289 | F22: Cortado
A23: 45354 | B23: 45354.519 | C23: card | D23: ANON-0000-0000-0012 | E23: 289 | F23: Americano
A24: 45354 | B24: 45354.548 | C24: card | D24: ANON-0000-0000-0017 | E24: 387 | F24: Hot Chocolate
A25: 45354 | B25: 45354.713 | C25: card | D25: ANON-0000-0000-0018 | E25: 387 | F25: Cocoa
A26: 45354 | B26: 45354.714 | C26: card | D26: ANON-0000-0000-0019 | E26: 289 | F26: Cortado
A27: 45354 | B27: 45354.752 | C27: card | D27: ANON-0000-0000-0020 | E27: 338 | F27: Americano with Milk
A28: 45354 | B28: 45354.753 | C28: card | D28: ANON-0000-0000-0020 | E28: 338 | F28: Americano with Milk
A29: 45354 | B29: 45354.756 | C29: card | D29: ANON-0000-0000-0020 | E29: 387 | F29: Hot Chocolate
A30: 45355 | B30: 45355.419 | C30: card | D30: ANON-0000-0000-0001 | E30: 387 | F30: Latte
A31: 45355 | B31: 45355.455 | C31: card | D31: ANON-0000-0000-0021 | E31: 387 | F31: Latte
A32: 45355 | B32: 45355.462 | C32: card | D32: ANON-0000-0000-0012 | E32: 338 | F32: Americano with Milk
... A42: 45356 | B42: 45356.751 | C42: card | D42: ANON-0000-0000-0028 | E42: 387 | F42: Hot Chocolate
A43: 45357 | B43: 45357.521 | C43: cash | E43: 350 | F43: Americano with Milk
A44: 45357 | B44: 45357.558 | C44: card | D44: ANON-0000-0000-0012 | E44: 289 | F44: Americano
A45: 45357 | B45: 45357.559 | C45: card | D45: ANON-0000-0000-0012 | E45: 289 | F45: Cortado
A46: 45357 | B46: 45357.619 | C46: card | D46: ANON-0000-0000-0029 | E46: 387 | F46: Cappuccino
A47: 45357 | B47: 45357.62 | C47: card | D47: ANON-0000-0000-0029 | E47: 387 | F47: Cappuccino
A48: 45358 | B48: 45358.423 | C48: cash | E48: 400 | F48: Latte
A49: 45358 | B49: 45358.43 | C49: card | D49: ANON-0000-0000-0030 | E49: 387 | F49: Hot Chocolate
A50: 45358 | B50: 45358.461 | C50: card | D50: ANON-0000-0000-0031 | E50: 387 | F50: Latte
A51: 45358 | B51: 45358.476 | C51: cash | E51: 400 | F51: Latte
A52: 45358 | B52: 45358.653 | C52: card | D52: ANON-0000-0000-0032 | E52: 289 | F52: Americano
A53: 45358 | B53: 45358.654 | C53: card | D53: ANON-0000-0000-0033 | E53: 338 | F53: Americano with Milk
A54: 45359 | B54: 45359.441 | C54: card | D54: ANON-0000-0000-0012 | E54: 289 | F54: Cortado
A55: 45359 | B55: 45359.516 | C55: card | D55: ANON-0000-0000-0034 | E55: 387 | F55: Cappuccino
A56: 45359 | B56: 45359.578 | C56: card | D56: ANON-0000-0000-0035 | E56: 289 | F56: Americano
A57: 45359 | B57: 45359.614 | C57: card | D57: ANON-0000-0000-0012 | E57: 289 | F57: Americano
A58: 45359 | B58: 45359.615 | C58: card | D58: ANON-0000-0000-0033 | E58: 289 | F58: Americano
A59: 45359 | B59: 45359.615 | C59: card | D59: ANON-0000-0000-0012 | E59: 338 | F59: Americano with Milk
A60: 45359 | B60: 45359.79 | C60: card | D60: ANON-0000-0000-0036 | E60: 387 | F60: Latte
A61: 45359 | B61: 45359.791 | C61: card | D61: ANON-0000-0000-0037 | E61: 387 | F61: Latte
A62: 45360 | B62: 45360.493 | C62: cash | E62: 400 | F62: Hot Chocolate
A63: 45360 | B63: 45360.504 | C63: card | D63: ANON-0000-0000-0038 | E63: 240 | F63: Espresso
A64: 45360 | B64: 45360.505 | C64: card | D64: ANON-0000-0000-0039 | E64: 289 | F64: Americano
A65: 45360 | B65: 45360.507 | C65: card | D65: ANON-0000-0000-0012 | E65: 387 | F65: Cappuccino
A66: 45360 | B66: 45360.509 | C66: card | D66: ANON-0000-0000-0040 | E66: 289 | F66: Americano
A67: 45360 | B67: 45360.51 | C67: card | D67: ANON-0000-0000-0040 | E67: 289 | F67: Americano
A68: 45360 | B68: 45360.548 | C68: card | D68: ANON-0000-0000-0041 | E68: 387 | F68: Latte
A69: 45360 | B69: 45360.57 | C69: card | D69: ANON-0000-0000-0042 | E69: 338 | F69: Americano with Milk
A70: 45360 | B70: 45360.579 | C70: card | D70: ANON-0000-0000-0043 | E70: 289 | F70: Cortado
A71: 45360 | B71: 45360.58 | C71: card | D71: ANON-0000-0000-0043 | E71: 387 | F71: Cappuccino
A72: 45360 | B72: 45360.589 | C72: card | D72: ANON-0000-0000-0009 | E72: 338 | F72: Americano with Milk
A73: 45360 | B73: 45360.602 | C73: card | D73: ANON-0000-0000-0044 | E73: 387 | F73: Hot Chocolate
A74: 45360 | B74: 45360.804 | C74: card | D74: ANON-0000-0000-0009 | E74: 387 | F74: Cappuccino
A75: 45360 | B75: 45360.805 | C75: card | D75: ANON-0000-0000-0009 | E75: 387 | F75: Hot Chocolate
A76: 45361 | B76: 45361.322 | C76: cash | E76: 300 | F76: Americano
A77: 45361 | B77: 45361.323 | C77: cash | E77: 350 | F77: Americano with Milk
A78: 45361 | B78: 45361.421 | C78: cash | E78: 400 | F78: Latte
A79: 45361 | B79: 45361.472 | C79: card | D79: ANON-0000-0000-0045 | E79: 240 | F79: Espresso
A80: 45361 | B80: 45361.744 | C80: cash | E80: 350 | F80: Americano with Milk
A81: 45361 | B81: 45361.815 | C81: card | D81: ANON-0000-0000-0046 | E81: 387 | F81: Latte
A82: 45361 | B82: 45361.817 | C82: card | D82: ANON-0000-0000-0046 | E82: 289 | F82: Cortado
A83: 45362 | B83: 45362.43 | C83: cash | E83: 400 | F83: Latte
A84: 45362 | B84: 45362.475 | C84: cash | E84: 400 | F84: Cappuccino
A85: 45362 | B85: 45362.476 | C85: cash | E85: 300 | F85: Cortado
A86: 45362 | B86: 45362.477 | C86: cash | E86: 300 | F86: Americano
A87: 45362 | B87: 45362.481 | C87: card | D87: ANON-0000-0000-0035 | E87: 387 | F87: Cappuccino
A88: 45362 | B88: 45362.684 | C88: card | D88: ANON-0000-0000-0047 | E88: 289 | F88: Americano
A89: 45362 | B89: 45362.685 | C89: card | D89: ANON-0000-0000-0047 | E89: 387 | F89: Latte
A90: 45362 | B90: 45362.702 | C90: card | D90: ANON-0000-0000-0048 | E90: 289 | F90: Cortado
A91: 45363 | B91: 45363.427 | C91: cash | E91: 400 | F91: Latte
A92: 45363 | B92: 45363.427 | C92: card | D92: ANON-0000-0000-0033 | E92: 289 | F92: Americano
A93: 45363 | B93: 45363.428 | C93: card | D93: ANON-0000-0000-0033 | E93: 289 | F93: Cortado
A94: 45363 | B94: 45363.473 | C94: card | D94: ANON-0000-0000-0049 | E94: 387 | F94: Hot Chocolate
A95: 45363 | B95: 45363.532 | C95: card | D95: ANON-0000-0000-0004 | E95: 338 | F95: Americano with Milk
A96: 45363 | B96: 45363.533 | C96: card | D96: ANON-0000-0000-0004 | E96: 289 | F96: Americano
A97: 45363 | B97: 45363.678 | C97: card | D97: ANON-0000-0000-0050 | E97: 289 | F97: Americano
A98: 45364 | B98: 45364.463 | C98: card | D98: ANON-0000-0000-0048 | E98: 387 | F98: Hot Chocolate
A99: 45364 | B99: 45364.492 | C99: card | D99: ANON-0000-0000-0004 | E99: 289 | F99: Americano
A100: 45364 | B100: 45364.513 | C100: card | D100: ANON-0000-0000-0051 | E100: 289 | F100: Americano
A101: 45364 | B101: 45364.513 | C101: card | D101: ANON-0000-0000-0051 | E101: 289 | F101: Americano
A102: 45364 | B102: 45364.524 | C102: cash | E102: 250 | F102: Espresso
A103: 45364 | B103: 45364.602 | C103: card | D103: ANON-0000-0000-0052 | E103: 338 | F103: Americano with Milk
A104: 45364 | B104: 45364.653 | C104: card | D104: ANON-0000-0000-0053 | E104: 240 | F104: Espresso
A105: 45364 | B105: 45364.654 | C105: card | D105: ANON-0000-0000-0053 | E105: 240 | F105: Espresso
A106: 45364 | B106: 45364.699 | C106: card | D106: ANON-0000-0000-0054 | E106: 240 | F106: Espresso
A107: 45365 | B107: 45365.418 | C107: cash | E107: 400 | F107: Latte
A108: 45365 | B108: 45365.436 | C108: card | D108: ANON-0000-0000-0055 | E108: 387 | F108: Latte
A109: 45365 | B109: 45365.437 | C109: card | D109: ANON-0000-0000-0055 | E109: 387 | F109: Hot Chocolate
...

Sheet Transform Data
A1: Date | B1: Time | C1: Payment Method | D1: Card Id | E1: Price | F1: Coffee Name | G1: Month | H1: Hour | I1: Is_Repeat | J1: Exclude_Cash | K1: Transaction_Id
A2: 45352 | B2: 0.42766204 | C2: card | D2: ANON-0000-0000-0001 | E2: 38.7 | F2: Latte | G2: =TEXT(Transform_Data[[#This Row],[Date]],"mmm yyyy") -> Mar 2024 | H2: =HOUR(Transform_Data[[#This Row],[Time]]) -> 10 | I2: =IF(COUNTIF('Transform Data'!$D:$D,'Transform Data'!D2)>1,"Repeat","Single") -> Repeat | J2: =IF('Transform Data'!D2="Cash","Cash",IF(COUNTIF('Transform Data'!$D:$D,'Transform Data'!D2)>1,"Repeat","Single")) -> Repeat | K2: ="TRANS-"&TEXT(ROW(A1),"0000") -> TRANS-0001
A3: 45352 | B3: 0.51344907 | C3: card | D3: ANON-0000-0000-0002 | E3: 38.7 | F3: Hot Chocolate | G3: =TEXT(Transform_Data[[#This Row],[Date]],"mmm yyyy") -> Mar 2024 | H3: =HOUR(Transform_Data[[#This Row],[Time]]) -> 12 | I3: =IF(COUNTIF('Transform Data'!$D:$D,'Transform Data'!D3)>1,"Repeat","Single") -> Repeat | J3: =IF('Transform Data'!D3="Cash","Cash",IF(COUNTIF('Transform Data'!$D:$D,'Transform Data'!D3)>1,"Repeat","Single")) -> Repeat | K3: ="TRANS-"&TEXT(ROW(A2),"0000") -> TRANS-0002
A4: 45352 | B4: 0.51409722 | C4: card | D4: ANON-0000-0000-0002 | E4: 38.7 | F4: Hot Chocolate | G4: =TEXT(Transform_Data[[#This Row],[Date]],"mmm yyyy") -> Mar 2024 | H4: =HOUR(Transform_Data[[#This Row],[Time]]) -> 12 | I4: =IF(COUNTIF('Transform Data'!$D:$D,'Transform Data'!D4)>1,"Repeat","Single") -> Repeat | J4: =IF('Transform Data'!D4="Cash","Cash",IF(COUNTIF('Transform Data'!$D:$D,'Transform Data'!D4)>1,"Repeat","Single")) -> Repeat | K4: ="TRANS-"&TEXT(ROW(A3),"0000") -> TRANS-0003
A5: 45352 | B5: 0.57399306 | C5: card | D5: ANON-0000-0000-0003 | E5: 28.9 | F5: Americano | G5: =TEXT(Transform_Data[[#This Row],[Date]],"mmm yyyy") -> Mar 2024 | H5: =HOUR(Transform_Data[[#This Row],[Time]]) -> 13 | I5: =IF(COUNTIF('Transform Data'!$D:$D,'Transform Data'!D5)>1,"Repeat","Single") -> Repeat | J5: =IF('Transform Data'!D5="Cash","Cash",IF(COUNTIF('Transform Data'!$D:$D,'Transform Data'!D5)>1,"Repeat","Single")) -> Repeat | K5: ="TRANS-"&TEXT(ROW(A4),"0000") -> TRANS-0004
A6: 45352 | B6: 0.57516204 | C6: card | D6: ANON-0000-0000-0004 | E6: 38.7 | F6: Latte | G6: =TEXT(Transform_Data[[#This Row],[Date]],"mmm yyyy") -> Mar 2024 | H6: =HOUR(Transform_Data[[#This Row],[Time]]) -> 13 | I6: =IF(COUNTIF('Transform Data'!$D:$D,'Transform Data'!D6)>1,"Repeat","Single") -> Repeat | J6: =IF('Transform Data'!D6="Cash","Cash",IF(COUNTIF('Transform Data'!$D:$D,'Transform Data'!D6)>1,"Repeat","Single")) -> Repeat | K6: ="TRANS-"&TEXT(ROW(A5),"0000") -> TRANS-0005
A7: 45352 | B7: 0.65262731 | C7: card | D7: ANON-0000-0000-0005 | E7: 33.8 | F7: Americano with Milk | G7: =TEXT(Transform_Data[[#This Row],[Date]],"mmm yyyy") -> Mar 2024 | H7: =HOUR(Transform_Data[[#This Row],[Time]]) -> 15 | I7: =IF(COUNTIF('Transform Data'!$D:$D,'Transform Data'!D7)>1,"Repeat","Single") -> Single | J7: =IF('Transform Data'!D7="Cash","Cash",IF(COUNTIF('Transform Data'!$D:$D,'Transform Data'!D7)>1,"Repeat","Single")) -> Single | K7: ="TRANS-"&TEXT(ROW(A6),"0000") -> TRANS-0006
A8: 45352 | B8: 0.67988426 | C8: card | D8: ANON-0000-0000-0006 | E8: 38.7 | F8: Hot Chocolate | G8: =TEXT(Transform_Data[[#This Row],[Date]],"mmm yyyy") -> Mar 2024 | H8: =HOUR(Transform_Data[[#This Row],[Time]]) -> 16 | I8: =IF(COUNTIF('Transform Data'!$D:$D,'Transform Data'!D8)>1,"Repeat","Single") -> Single | J8: =IF('Transform Data'!D8="Cash","Cash",IF(COUNTIF('Transform Data'!$D:$D,'Transform Data'!D8)>1,"Repeat","Single")) -> Single | K8: ="TRANS-"&TEXT(ROW(A7),"0000") -> TRANS-0007
A9: 45352 | B9: 0.77711806 | C9: card | D9: ANON-0000-0000-0007 | E9: 33.8 | F9: Americano with Milk | G9: =TEXT(Transform_Data[[#This Row],[Date]],"mmm yyyy") -> Mar 2024 | H9: =HOUR(Transform_Data[[#This Row],[Time]]) -> 18 | I9: =IF(COUNTIF('Transform Data'!$D:$D,'Transform Data'!D9)>1,"Repeat","Single") -> Single | J9: =IF('Transform Data'!D9="Cash","Cash",IF(COUNTIF('Transform Data'!$D:$D,'Transform Data'!D9)>1,"Repeat","Single")) -> Single | K9: ="TRANS-"&TEXT(ROW(A8),"0000") -> TRANS-0008
A10: 45352 | B10: 0.80695602 | C10: card | D10: ANON-0000-0000-0008 | E10: 38.7 | F10: Cocoa | G10: =TEXT(Transform_Data[[#This Row],[Date]],"mmm yyyy") -> Mar 2024 | H10: =HOUR(Transform_Data[[#This Row],[Time]]) -> 19 | I10: =IF(COUNTIF('Transform Data'!$D:$D,'Transform Data'!D10)>1,"Repeat","Single") -> Repeat | J10: =IF('Transform Data'!D10="Cash","Cash",IF(COUNTIF('Transform Data'!$D:$D,'Transform Data'!D10)>1,"Repeat","Single")) -> Repeat | K10: ="TRANS-"&TEXT(ROW(A9),"0000") -> TRANS-0009
A11: 45352 | B11: 0.8078125 | C11: card | D11: ANON-0000-0000-0008 | E11: 33.8 | F11: Americano with Milk | G11: =TEXT(Transform_Data[[#This Row],[Date]],"mmm yyyy") -> Mar 2024 | H11: =HOUR(Transform_Data[[#This Row],[Time]]) -> 19 | I11: =IF(COUNTIF('Transform Data'!$D:$D,'Transform Data'!D11)>1,"Repeat","Single") -> Repeat | J11: =IF('Transform Data'!D11="Cash","Cash",IF(COUNTIF('Transform Data'!$D:$D,'Transform Data'!D11)>1,"Repeat","Single")) -> Repeat | K11: ="TRANS-"&TEXT(ROW(A10),"0000") -> TRANS-0010
A12: 45352 | B12: 0.81200231 | C12: card | D12: ANON-0000-0000-0009 | E12: 33.8 | F12: Americano with Milk | G12: =TEXT(Transform_Data[[#This Row],[Date]],"mmm yyyy") -> Mar 2024 | H12: =HOUR(Transform_Data[[#This Row],[Time]]) -> 19 | I12: =IF(COUNTIF('Transform Data'!$D:$D,'Transform Data'!D12)>1,"Repeat","Single") -> Repeat | J12: =IF('Transform Data'!D12="Cash","Cash",IF(COUNTIF('Transform Data'!$D:$D,'Transform Data'!D12)>1,"Repeat","Single")) -> Repeat | K12: ="TRANS-"&TEXT(ROW(A11),"0000") -> TRANS-0011
A13: 45353 | B13: 0.43201389 | C13: card | D13: ANON-0000-0000-0010 | E13: 28.9 | F13: Americano | G13: =TEXT(Transform_Data[[#This Row],[Date]],"mmm yyyy") -> Mar 2024 | H13: =HOUR(Transform_Data[[#This Row],[Time]]) -> 10 | I13: =IF(COUNTIF('Transform Data'!$D:$D,'Transform Data'!D13)>1,"Repeat","Single") -> Single | J13: =IF('Transform Data'!D13="Cash","Cash",IF(COUNTIF('Transform Data'!$D:$D,'Transform Data'!D13)>1,"Repeat","Single")) -> Single | K13: ="TRANS-"&TEXT(ROW(A12),"0000") -> TRANS-0012
... A3637: 45739 | B3637: 0.7580787 | C3637: card | D3637: ANON-0000-0000-1275 | E3637: 35.76 | F3637: Latte | G3637: =TEXT(Transform_Data[[#This Row],[Date]],"mmm yyyy") -> Mar 2025 | H3637: =HOUR(Transform_Data[[#This Row],[Time]]) -> 18 | I3637: =IF(COUNTIF('Transform Data'!$D:$D,'Transform Data'!D3637)>1,"Repeat","Single") -> Repeat | J3637: =IF('Transform Data'!D3637="Cash","Cash",IF(COUNTIF('Transform Data'!$D:$D,'Transform Data'!D3637)>1,"Repeat","Single")) -> Repeat | K3637: ="TRANS-"&TEXT(ROW(A3636),"0000") -> TRANS-3636

Sheet Dashboard

Sheet Pivot KPI
A3: Sum of Price | B3: Count of Transaction_Id | C3: Avg Revenue / Transaction | D3: % Repeat Customer
A4: 115431.58 | B4: 3636 | C4: =GETPIVOTDATA("Sum of Price",$A$3)/GETPIVOTDATA("Count of Transaction_Id",$A$3) -> 31.746859 | D4: =GETPIVOTDATA("Card Id",'Pivot Repeat'!$A$3,"Exclude_Cash","Repeat")/(GETPIVOTDATA("Card Id",'Pivot Repeat'!$A$3,"Exclude_Cash","Repeat")+GETPIVOTDATA("Card Id",'Pivot Repeat'!$A$3,"Exclude_Cash","Single")) -> 0.78263321

Sheet Pivot Repeat
A3: Row Labels | B3: Count of Card Id
A4: Cash | B4: 89
A5: Repeat | B5: 2776
A6: Single | B6: 771
A7: Grand Total | B7: 3636

Sheet Pivot Product
A3: Row Labels | B3: Revenue | J3: Row Labels | K3: Count of Transaction_Id
A4: Espresso | B4: 2814.28 | J4: Americano with Milk | K4: 824
A5: Cortado | B5: 7534.86 | J5: Latte | K5: 782
A6: Cocoa | B6: 8678.16 | J6: Americano | K6: 578
A7: Hot Chocolate | B7: 10172.46 | J7: Cappuccino | K7: 501
A8: Americano | B8: 15062.26 | J8: Cortado | K8: 292
A9: Cappuccino | B9: 18034.14 | J9: Hot Chocolate | K9: 282
A10: Americano with Milk | B10: 25269.12 | J10: Cocoa | K10: 243
A11: Latte | B11: 27866.3 | J11: Espresso | K11: 134
A12: Grand Total | B12: 115431.58 | J12: Grand Total | K12: 3636

Sheet Pivot Time
A1: Monthly Trend | E1: Hourly Sales
A3: Row Labels | B3: Sum of Price | E3: Row Labels | F3: Count of Transaction_Id
A4: Jan | B4: 6398.86 | E4: 06 | F4: 5
A5: Feb | B5: 13215.48 | E5: 07 | F5: 91
A6: Mar | B6: 17036.64 | E6: 08 | F6: 235
A7: Apr | B7: 6720.56 | E7: 09 | F7: 247
A8: May | B8: 9063.42 | E8: 10 | F8: 349
A9: Jun | B9: 7758.76 | E9: 11 | F9: 294
A10: Jul | B10: 6915.94 | E10: 12 | F10: 249
A11: Aug | B11: 7613.84 | E11: 13 | F11: 227
A12: Sep | B12: 9988.64 | E12: 14 | F12: 228
A13: Oct | B13: 13891.16 | E13: 15 | F13: 245
A14: Nov | B14: 8590.54 | E14: 16 | F14: 283
A15: Dec | B15: 8237.74 | E15: 17 | F15: 244
A16: Grand Total | B16: 115431.58 | E16: 18 | F16: 220
E17: 19 | F17: 235
E18: 20 | F18: 171
E19: 21 | F19: 197
E20: 22 | F20: 116
E21: Grand Total | F21: 3636

Sheet Pivot Payment
A3: Row Labels | B3: Count of Transaction_Id | D3: Card Transactions | E3: =GETPIVOTDATA("Transaction_Id",$A$3,"Payment Method","card") -> 3547 | F3: =E3/$E$5 -> 0.97552255 | G3: ="Transactions Card : "&E3&" ("&TEXT(F3,"0%")&")" -> Transactions Card : 3547 (98%)
A4: card | B4: 3547 | D4: Cash Transactions | E4: =GETPIVOTDATA("Transaction_Id",$A$3,"Payment Method","cash") -> 89 | F4: =E4/$E$5 -> 0.024477448 | G4: ="Transactions Cash : "&E4&" ("&TEXT(F4,"0%")&")" -> Transactions Cash : 89 (2%)
A5: cash | B5: 89 | D5: Total | E5: =SUM(B4:B5) -> 3636 | F5: =E5/$E$5 -> 1
A6: Grand Total | B6: 3636
